README.md
csv_writer.py
dataframe_converter.py
setup.cfg
setup.py
twarc_csv.py
twarc_csv.egg-info/PKG-INFO
twarc_csv.egg-info/SOURCES.txt
twarc_csv.egg-info/dependency_links.txt
twarc_csv.egg-info/entry_points.txt
twarc_csv.egg-info/requires.txt
twarc_csv.egg-info/top_level.txt