Metadata-Version: 2.1
Name: twarc-csv
Version: 0.5.1
Summary: A twarc plugin to output Twitter data as CSV
Home-page: https://github.com/docnow/twarc-csv
Author: Igor Brigadir
Author-email: igor.brigadir@gmail.com
License: UNKNOWN
Platform: UNKNOWN
Requires-Python: >=3.3
